pytest_pspec/__init__.py
pytest_pspec/formatters.py
pytest_pspec/models.py
pytest_pspec/plugin.py
pytest_pspec/wrappers.py
pytest_pspec-0.0.4.data/scripts/pspec
pytest_pspec-0.0.4.dist-info/LICENSE
pytest_pspec-0.0.4.dist-info/METADATA
pytest_pspec-0.0.4.dist-info/WHEEL
pytest_pspec-0.0.4.dist-info/entry_points.txt
pytest_pspec-0.0.4.dist-info/top_level.txt
pytest_pspec-0.0.4.dist-info/RECORD
