Metadata-Version: 2.1
Name: pytest-pspec
Version: 0.0.4
Summary: A rspec format reporter for Python ptest
Home-page: https://github.com/gowtham-sai/pytest-pspec
Author: Gowtham Sai
Author-email: hello@gowtham-sai.com
License: UNKNOWN
Keywords: pytest pspec test report bdd rspec
Platform: UNKNOWN
Classifier: Development Status :: 4 - Beta
Classifier: Framework :: Pytest
Classifier: Intended Audience :: Developers
Classifier: Topic :: Software Development :: Testing
Classifier: Programming Language :: Python
Classifier: Programming Language :: Python :: 2
Classifier: Programming Language :: Python :: 2.7
Classifier: Programming Language :: Python :: 3
Classifier: Programming Language :: Python :: 3.4
Classifier: Programming Language :: Python :: 3.5
Classifier: Programming Language :: Python :: Implementation :: CPython
Classifier: Programming Language :: Python :: Implementation :: PyPy
Classifier: Operating System :: OS Independent
Classifier: License :: OSI Approved :: MIT License
Requires-Dist: pytest (>=3.0.0)
Requires-Dist: six (>=1.11.0)
